is_valid_postgres_column_name/__init__.py
is_valid_postgres_column_name/constants.py
is_valid_postgres_column_name/main.py
is_valid_postgres_column_name/py.typed
is_valid_postgres_column_name/reserved_keywords/10.txt
is_valid_postgres_column_name/reserved_keywords/11.txt
is_valid_postgres_column_name/reserved_keywords/12.txt
is_valid_postgres_column_name/reserved_keywords/13.txt
is_valid_postgres_column_name/reserved_keywords/7.1.txt
is_valid_postgres_column_name/reserved_keywords/7.2.txt
is_valid_postgres_column_name/reserved_keywords/7.3.txt
is_valid_postgres_column_name/reserved_keywords/7.4.txt
is_valid_postgres_column_name/reserved_keywords/8.0.txt
is_valid_postgres_column_name/reserved_keywords/8.1.txt
is_valid_postgres_column_name/reserved_keywords/8.2.txt
is_valid_postgres_column_name/reserved_keywords/8.3.txt
is_valid_postgres_column_name/reserved_keywords/8.4.txt
is_valid_postgres_column_name/reserved_keywords/9.0.txt
is_valid_postgres_column_name/reserved_keywords/9.1.txt
is_valid_postgres_column_name/reserved_keywords/9.2.txt
is_valid_postgres_column_name/reserved_keywords/9.3.txt
is_valid_postgres_column_name/reserved_keywords/9.4.txt
is_valid_postgres_column_name/reserved_keywords/9.5.txt
is_valid_postgres_column_name/reserved_keywords/9.6.txt
is_valid_postgres_column_name-0.0.2.dist-info/LICENSE
is_valid_postgres_column_name-0.0.2.dist-info/METADATA
is_valid_postgres_column_name-0.0.2.dist-info/WHEEL
is_valid_postgres_column_name-0.0.2.dist-info/top_level.txt
is_valid_postgres_column_name-0.0.2.dist-info/RECORD
