Metadata-Version: 2.1
Name: is-valid-postgres-column-name
Version: 0.0.2
Summary: Allows you to check if a given string can be PostgreSQL column name
Home-page: https://github.com/tomwojcik/is_valid_postgres_column
Author: Tom Wojcik
License: MIT
Download-URL: https://github.com/tomwojcik/is_valid_postgres_column/archive/0.0.2.tar.gz
Keywords: psycopg2,psycopg3,postgres,postgresql
Platform: any
Classifier: Development Status :: 4 - Beta
Classifier: Intended Audience :: Developers
Classifier: Topic :: Software Development :: Build Tools
Classifier: License :: OSI Approved :: MIT License
Classifier: Programming Language :: Python :: 3.7
Classifier: Programming Language :: Python :: 3.8
Classifier: Programming Language :: Python :: 3.9
Requires-Python: >=3.0
